AUTHORS
ChangeLog
LICENSE
PKG-INFO
README.rst
setup.cfg
setup.py
pyundo/__init__.py
pyundo/exceptions.py
pyundo/flow.py
pyundo/task.py
pyundo.egg-info/PKG-INFO
pyundo.egg-info/SOURCES.txt
pyundo.egg-info/dependency_links.txt
pyundo.egg-info/not-zip-safe
pyundo.egg-info/pbr.json
pyundo.egg-info/top_level.txt