Metadata-Version: 1.1
Name: pyundo
Version: 0.1
Summary: A task flow in Python with do and undo
Home-page: https://github.com/xgfone/pyundo
Author: xgfone
Author-email: xgfone@126.com
License: UNKNOWN
Platform: UNKNOWN
Classifier: License :: OSI Approved :: Apache Software License
Classifier: Programming Language :: Python
Classifier: Programming Language :: Python :: 2
Classifier: Programming Language :: Python :: 2.7
Classifier: Programming Language :: Python :: 3
Classifier: Programming Language :: Python :: 3.3
Classifier: Programming Language :: Python :: 3.4
Classifier: Programming Language :: Python :: 3.5
